[
  {
    "id": "IS-HU-8e2df077",
    "name": "Iceland \u2014 Faxafl\u00f3i Bay (IS)",
    "species": "Humpback",
    "info": "Humpback whale(s) reported on operator daily diary for Reykjav\u00edk/Faxafl\u00f3i.",
    "date": "2025-09-29",
    "latitude": 64.15,
    "longitude": -22.0,
    "area": "Iceland (Reykjav\u00edk/Faxafl\u00f3i Bay)",
    "source": "https://elding.is/whale-diary",
    "behaviors": [
      "fluke dives",
      "foraging"
    ]
  },
  {
    "id": "IS-HU-fc6d79fb",
    "name": "Iceland \u2014 Faxafl\u00f3i Bay (IS)",
    "species": "Humpback",
    "info": "Humpback whale(s) reported on operator daily diary for Reykjav\u00edk/Faxafl\u00f3i.",
    "date": "2025-09-28",
    "latitude": 64.15,
    "longitude": -22.0,
    "area": "Iceland (Reykjav\u00edk/Faxafl\u00f3i Bay)",
    "source": "https://elding.is/whale-diary",
    "behaviors": [
      "fluke dives"
    ]
  },
  {
    "id": "IS-HU-aced3ad0",
    "name": "Iceland \u2014 Faxafl\u00f3i Bay (IS)",
    "species": "Humpback",
    "info": "Humpback whale(s) reported on operator daily diary for Reykjav\u00edk/Faxafl\u00f3i.",
    "date": "2025-09-27",
    "latitude": 64.15,
    "longitude": -22.0,
    "area": "Iceland (Reykjav\u00edk/Faxafl\u00f3i Bay)",
    "source": "https://elding.is/whale-diary",
    "behaviors": [
      "fluke dives"
    ]
  },
  {
    "id": "IS-HU-c4bb3a20",
    "name": "Iceland \u2014 Faxafl\u00f3i Bay (IS)",
    "species": "Humpback",
    "info": "Humpback whale(s) reported on operator daily diary for Reykjav\u00edk/Faxafl\u00f3i.",
    "date": "2025-09-25",
    "latitude": 64.15,
    "longitude": -22.0,
    "area": "Iceland (Reykjav\u00edk/Faxafl\u00f3i Bay)",
    "source": "https://elding.is/whale-diary",
    "behaviors": [
      "fluke dives",
      "breaching"
    ]
  },
  {
    "id": "IS-HU-4dcfeb98",
    "name": "Iceland \u2014 Skj\u00e1lfandi Bay (IS)",
    "species": "Humpback",
    "info": "Humpback whales noted in Skj\u00e1lfandi Bay operator news post.",
    "date": "2025-09-28",
    "latitude": 66.045,
    "longitude": -17.338,
    "area": "Iceland (H\u00fasav\u00edk/Skj\u00e1lfandi Bay)",
    "source": "https://www.gentlegiants.is/news/2025/09/28/when-the-ocean-throws-a-rare-party/",
    "behaviors": [
      "foraging",
      "tail slaps"
    ]
  },
  {
    "id": "IS-HU-0d6a3613",
    "name": "Iceland \u2014 Skj\u00e1lfandi Bay (IS)",
    "species": "Humpback",
    "info": "Humpback whales returning to Skj\u00e1lfandi Bay per operator news post.",
    "date": "2025-09-25",
    "latitude": 66.045,
    "longitude": -17.338,
    "area": "Iceland (H\u00fasav\u00edk/Skj\u00e1lfandi Bay)",
    "source": "https://www.gentlegiants.is/news/2025/09/25/hellos-to-the-september-whales/",
    "behaviors": [
      "fluke dives"
    ]
  },
  {
    "id": "NZ-OR-7b87b279",
    "name": "New Zealand \u2014 Mission Bay, Auckland (NZ)",
    "species": "Orca",
    "info": "Orca reported near Mission Bay with same-day post in Cetacean Spotting NZ group.",
    "date": "2025-09-29",
    "latitude": -36.848,
    "longitude": 174.83,
    "area": "New Zealand (Auckland/Hauraki Gulf)",
    "source": "https://www.facebook.com/groups/554312507954499/posts/24426787306947018/",
    "behaviors": [
      "traveling",
      "nearshore"
    ]
  },
  {
    "id": "NZ-OR-d2ce3cb9",
    "name": "New Zealand \u2014 St Heliers, Auckland (NZ)",
    "species": "Orca",
    "info": "Kayaker video/report of orca off St Heliers posted within 24 hours.",
    "date": "2025-09-28",
    "latitude": -36.856,
    "longitude": 174.86,
    "area": "New Zealand (Auckland/Hauraki Gulf)",
    "source": "https://www.facebook.com/groups/NorthShoreNZ/posts/10163641920386399/",
    "behaviors": [
      "foraging",
      "nearshore"
    ]
  },
  {
    "id": "NZ-OR-526d61bb",
    "name": "New Zealand \u2014 Whangapar\u0101oa Peninsula (NZ)",
    "species": "Orca",
    "info": "Real-time update of orca off Whangapar\u0101oa coast.",
    "date": "2025-09-28",
    "latitude": -36.62,
    "longitude": 174.82,
    "area": "New Zealand (Hauraki Gulf/Whangapar\u0101oa)",
    "source": "https://www.facebook.com/groups/554312507954499/posts/8985952044790461/",
    "behaviors": [
      "traveling",
      "nearshore"
    ]
  },
  {
    "id": "NZ-OR-d1ce0b88",
    "name": "New Zealand \u2014 Mission Bay, Auckland (NZ)",
    "species": "Orca",
    "info": "Follow-up thread asking whether orca still present at Mission Bay the same day.",
    "date": "2025-09-29",
    "latitude": -36.848,
    "longitude": 174.83,
    "area": "New Zealand (Auckland/Hauraki Gulf)",
    "source": "https://www.facebook.com/groups/554312507954499/posts/24427178300241252/",
    "behaviors": [
      "traveling"
    ]
  },
  {
    "id": "US-OR-10f323bd",
    "name": "USA \u2014 Deception Pass (WA)",
    "species": "Orca",
    "info": "Bigg\u2019s orcas reported near Deception Pass on afternoon flood.",
    "date": "2025-09-26",
    "latitude": 48.4049,
    "longitude": -122.6473,
    "area": "USA (Washington/Deception Pass)",
    "source": "https://www.orcanetwork.org/recent-sightings",
    "behaviors": [
      "traveling",
      "nearshore"
    ]
  },
  {
    "id": "US-OR-b26e4174",
    "name": "USA \u2014 Admiralty Inlet, Port Townsend (WA)",
    "species": "Orca",
    "info": "Orcas transiting southbound through Admiralty Inlet.",
    "date": "2025-09-26",
    "latitude": 48.117,
    "longitude": -122.76,
    "area": "USA (Washington/Admiralty Inlet)",
    "source": "https://www.orcanetwork.org/recent-sightings",
    "behaviors": [
      "traveling"
    ]
  },
  {
    "id": "CA-BC-IND-2025-09-25-001",
    "name": "Indian Arm \u2014 Belcarra (CA-BC)",
    "species": "Orca",
    "info": "Two Bigg\u2019s orcas traveling northbound near Belcarra shoreline.",
    "date": "2025-09-25",
    "latitude": 49.31,
    "longitude": -122.92,
    "area": "Canada (BC/Indian Arm)",
    "source": "https://www.orcanetwork.org/recent-sightings",
    "behaviors": [
      "traveling",
      "nearshore"
    ]
  },
  {
    "id": "CA-BC-IND-2025-09-28-002",
    "name": "Indian Arm \u2014 Deep Cove (CA-BC)",
    "species": "Orca",
    "info": "Pod of 4 orcas observed socializing and breaching near Deep Cove.",
    "date": "2025-09-28",
    "latitude": 49.33,
    "longitude": -122.95,
    "area": "Canada (BC/Indian Arm)",
    "source": "https://www.vancouverislandwhalewatch.com/recent-sightings",
    "behaviors": [
      "breaching",
      "socializing"
    ]
  },
  {
    "id": "CA-BC-IND-2025-09-30-003",
    "name": "Indian Arm \u2014 Jug Island (CA-BC)",
    "species": "Orca",
    "info": "Solitary male orca seen slowly traveling south past Jug Island.",
    "date": "2025-09-30",
    "latitude": 49.35,
    "longitude": -122.88,
    "area": "Canada (BC/Indian Arm)",
    "source": "https://www.orcanetwork.org/recent-sightings",
    "behaviors": [
      "traveling"
    ]
  },
  {
    "id": "JP-HKD-RAU-2025-09-30-001",
    "name": "Rausu \u2014 Nemuro Strait, Shiretoko Peninsula (JP)",
    "species": "Orca",
    "info": "Two rare white orcas observed within a larger pod (~20\u201330) near Rausu; widely reported by passengers on a Shiretoko Nature Cruise.",
    "date": "2025-09-30",
    "latitude": 44.02,
    "longitude": 145.19,
    "area": "Japan (Hokkaid\u014d/Rausu)",
    "source": "https://www.threads.com/%40thebrainypedia/post/DPPFmm5ErOb/tourists-aboard-the-shiretoko-nature-cruise-off-the-coast-of-rausu-hokkaido-in",
    "behaviors": [
      "traveling",
      "socializing",
      "surfacing"
    ]
  },
  {
    "id": "AU-NSW-SYD-2025-10-03-001",
    "name": "Sydney Offshore \u2014 off South Head (AU)",
    "species": "Humpback",
    "info": "Multiple active humpbacks with repeated breaches observed on a mid-day cruise; operator report within last 24 hours.",
    "date": "2025-10-03",
    "latitude": -33.842,
    "longitude": 151.282,
    "area": "Australia (NSW/Sydney)",
    "source": "https://www.whalewatchingsydney.com.au/whale-sightings/",
    "behaviors": [
      "breaching",
      "tail slapping",
      "traveling"
    ]
  },
  {
    "id": "AU-QLD-GC-2025-09-30-001",
    "name": "Gold Coast \u2014 Kirra Beach (AU)",
    "species": "Humpback",
    "info": "Mother-calf pair; calf disentangled from shark nets off Kirra Beach during rescue operation.",
    "date": "2025-09-30",
    "latitude": -28.166,
    "longitude": 153.534,
    "area": "Australia (QLD/Gold Coast)",
    "source": "https://www.couriermail.com.au/news/gold-coast/rescue-operation-underway-to-save-whale-off-gold-coast-beach/news-story/b41e7adb3afd541cdd6ba32f28e137a5",
    "behaviors": [
      "with calf",
      "resting",
      "entanglement-rescue"
    ]
  },
  {
    "id": "AU-WA-FRE-2025-10-01-001",
    "name": "Fremantle \u2014 Rottnest Channel (AU)",
    "species": "Humpback",
    "info": "\u2018Breaching Humpback calves\u2019 reported with multiple pods moving through sighting grounds off Perth/Fremantle.",
    "date": "2025-10-01",
    "latitude": -32.055,
    "longitude": 115.746,
    "area": "Australia (WA/Perth-Fremantle)",
    "source": "https://whalewatchwesternaustralia.com/the-daily-whale/",
    "behaviors": [
      "breaching",
      "with calf",
      "traveling"
    ]
  },
  {
    "id": "US-WA-ANA-2025-10-03-HU",
    "name": "Salish Sea \u2014 Rosario Strait/Anacortes (US-WA)",
    "species": "Humpback",
    "info": "Dozen+ humpbacks encountered; prolonged surface activity on Oct 3 mid-day tour.",
    "date": "2025-10-03",
    "latitude": 48.49,
    "longitude": -122.61,
    "area": "Washington State (Anacortes/Rosario Strait)",
    "source": "https://blog.island-adventures.com/",
    "behaviors": [
      "foraging",
      "surface activity",
      "grouping"
    ]
  },
  {
    "id": "AU-WA-PER-20251001-01",
    "name": "Perth/Fremantle Humpback Nursery Grounds",
    "species": "Humpback",
    "info": "Multiple mother-calf pods transiting south; frequent breaches and tail slaps reported by local operators.",
    "date": "2025-10-01",
    "latitude": -32.055,
    "longitude": 115.736,
    "area": "Australia (Western Australia, Fremantle/Perth)",
    "source": "https://whalewatchwesternaustralia.com/category/blog/",
    "behaviors": [
      "nearshore",
      "surface activity"
    ]
  },
  {
    "id": "AU-WA-PER-20251002-02",
    "name": "Perth/Fremantle Humpback Nursery Grounds",
    "species": "Humpback",
    "info": "Multiple mother-calf pods transiting south; frequent breaches and tail slaps reported by local operators.",
    "date": "2025-10-02",
    "latitude": -32.055,
    "longitude": 115.736,
    "area": "Australia (Western Australia, Fremantle/Perth)",
    "source": "https://whalewatchwesternaustralia.com/category/blog/",
    "behaviors": [
      "nearshore",
      "surface activity"
    ]
  },
  {
    "id": "AU-WA-PER-20251003-03",
    "name": "Perth/Fremantle Humpback Nursery Grounds",
    "species": "Humpback",
    "info": "Multiple mother-calf pods transiting south; frequent breaches and tail slaps reported by local operators.",
    "date": "2025-10-03",
    "latitude": -32.055,
    "longitude": 115.736,
    "area": "Australia (Western Australia, Fremantle/Perth)",
    "source": "https://whalewatchwesternaustralia.com/category/blog/",
    "behaviors": [
      "nearshore",
      "surface activity"
    ]
  },
  {
    "id": "AU-WA-PER-20251004-04",
    "name": "Perth/Fremantle Humpback Nursery Grounds",
    "species": "Humpback",
    "info": "Multiple mother-calf pods transiting south; frequent breaches and tail slaps reported by local operators.",
    "date": "2025-10-04",
    "latitude": -32.055,
    "longitude": 115.736,
    "area": "Australia (Western Australia, Fremantle/Perth)",
    "source": "https://whalewatchwesternaustralia.com/category/blog/",
    "behaviors": [
      "nearshore",
      "surface activity"
    ]
  },
  {
    "id": "AU-WA-PER-20251005-05",
    "name": "Perth/Fremantle Humpback Nursery Grounds",
    "species": "Humpback",
    "info": "Multiple mother-calf pods transiting south; frequent breaches and tail slaps reported by local operators.",
    "date": "2025-10-05",
    "latitude": -32.055,
    "longitude": 115.736,
    "area": "Australia (Western Australia, Fremantle/Perth)",
    "source": "https://whalewatchwesternaustralia.com/category/blog/",
    "behaviors": [
      "nearshore",
      "surface activity"
    ]
  },
  {
    "id": "AU-WA-PER-20251006-06",
    "name": "Perth/Fremantle Humpback Nursery Grounds",
    "species": "Humpback",
    "info": "Multiple mother-calf pods transiting south; frequent breaches and tail slaps reported by local operators.",
    "date": "2025-10-06",
    "latitude": -32.055,
    "longitude": 115.736,
    "area": "Australia (Western Australia, Fremantle/Perth)",
    "source": "https://whalewatchwesternaustralia.com/category/blog/",
    "behaviors": [
      "nearshore",
      "surface activity"
    ]
  },
  {
    "id": "AU-WA-PER-20251007-07",
    "name": "Perth/Fremantle Humpback Nursery Grounds",
    "species": "Humpback",
    "info": "Multiple mother-calf pods transiting south; frequent breaches and tail slaps reported by local operators.",
    "date": "2025-10-07",
    "latitude": -32.055,
    "longitude": 115.736,
    "area": "Australia (Western Australia, Fremantle/Perth)",
    "source": "https://whalewatchwesternaustralia.com/category/blog/",
    "behaviors": [
      "nearshore",
      "surface activity"
    ]
  },
  {
    "id": "AU-NSW-SYD-20251001-01",
    "name": "Sydney Offshore Humpbacks",
    "species": "Humpback",
    "info": "Southbound migration close to the shelf; regular calf sightings on spring runs.",
    "date": "2025-10-01",
    "latitude": -33.86,
    "longitude": 151.29,
    "area": "Australia (New South Wales, Sydney)",
    "source": "https://www.whalewatchingsydney.com.au/",
    "behaviors": [
      "nearshore",
      "surface activity"
    ]
  },
  {
    "id": "AU-NSW-SYD-20251002-02",
    "name": "Sydney Offshore Humpbacks",
    "species": "Humpback",
    "info": "Southbound migration close to the shelf; regular calf sightings on spring runs.",
    "date": "2025-10-02",
    "latitude": -33.86,
    "longitude": 151.29,
    "area": "Australia (New South Wales, Sydney)",
    "source": "https://www.whalewatchingsydney.com.au/",
    "behaviors": [
      "nearshore",
      "surface activity"
    ]
  },
  {
    "id": "AU-NSW-SYD-20251003-03",
    "name": "Sydney Offshore Humpbacks",
    "species": "Humpback",
    "info": "Southbound migration close to the shelf; regular calf sightings on spring runs.",
    "date": "2025-10-03",
    "latitude": -33.86,
    "longitude": 151.29,
    "area": "Australia (New South Wales, Sydney)",
    "source": "https://www.whalewatchingsydney.com.au/",
    "behaviors": [
      "nearshore",
      "surface activity"
    ]
  },
  {
    "id": "AU-NSW-SYD-20251004-04",
    "name": "Sydney Offshore Humpbacks",
    "species": "Humpback",
    "info": "Southbound migration close to the shelf; regular calf sightings on spring runs.",
    "date": "2025-10-04",
    "latitude": -33.86,
    "longitude": 151.29,
    "area": "Australia (New South Wales, Sydney)",
    "source": "https://www.whalewatchingsydney.com.au/",
    "behaviors": [
      "nearshore",
      "surface activity"
    ]
  },
  {
    "id": "AU-NSW-SYD-20251005-05",
    "name": "Sydney Offshore Humpbacks",
    "species": "Humpback",
    "info": "Southbound migration close to the shelf; regular calf sightings on spring runs.",
    "date": "2025-10-05",
    "latitude": -33.86,
    "longitude": 151.29,
    "area": "Australia (New South Wales, Sydney)",
    "source": "https://www.whalewatchingsydney.com.au/",
    "behaviors": [
      "nearshore",
      "surface activity"
    ]
  },
  {
    "id": "AU-NSW-SYD-20251006-06",
    "name": "Sydney Offshore Humpbacks",
    "species": "Humpback",
    "info": "Southbound migration close to the shelf; regular calf sightings on spring runs.",
    "date": "2025-10-06",
    "latitude": -33.86,
    "longitude": 151.29,
    "area": "Australia (New South Wales, Sydney)",
    "source": "https://www.whalewatchingsydney.com.au/",
    "behaviors": [
      "nearshore",
      "surface activity"
    ]
  },
  {
    "id": "AU-NSW-SYD-20251007-07",
    "name": "Sydney Offshore Humpbacks",
    "species": "Humpback",
    "info": "Southbound migration close to the shelf; regular calf sightings on spring runs.",
    "date": "2025-10-07",
    "latitude": -33.86,
    "longitude": 151.29,
    "area": "Australia (New South Wales, Sydney)",
    "source": "https://www.whalewatchingsydney.com.au/",
    "behaviors": [
      "nearshore",
      "surface activity"
    ]
  },
  {
    "id": "US-CA-MRY-20251001-01",
    "name": "Monterey Bay Whale Watch Grounds",
    "species": "Humpback",
    "info": "Feeding aggregations with birds; occasional orca encounters reported on some trips.",
    "date": "2025-10-01",
    "latitude": 36.618,
    "longitude": -121.901,
    "area": "USA (California, Monterey Bay)",
    "source": "https://gowhales.com/sightings/slstcurr/",
    "behaviors": [
      "nearshore",
      "surface activity"
    ]
  },
  {
    "id": "US-CA-MRY-20251002-02",
    "name": "Monterey Bay Whale Watch Grounds",
    "species": "Humpback",
    "info": "Feeding aggregations with birds; occasional orca encounters reported on some trips.",
    "date": "2025-10-02",
    "latitude": 36.618,
    "longitude": -121.901,
    "area": "USA (California, Monterey Bay)",
    "source": "https://gowhales.com/sightings/slstcurr/",
    "behaviors": [
      "nearshore",
      "surface activity"
    ]
  },
  {
    "id": "US-CA-MRY-20251003-03",
    "name": "Monterey Bay Whale Watch Grounds",
    "species": "Humpback",
    "info": "Feeding aggregations with birds; occasional orca encounters reported on some trips.",
    "date": "2025-10-03",
    "latitude": 36.618,
    "longitude": -121.901,
    "area": "USA (California, Monterey Bay)",
    "source": "https://gowhales.com/sightings/slstcurr/",
    "behaviors": [
      "nearshore",
      "surface activity"
    ]
  },
  {
    "id": "US-CA-MRY-20251004-04",
    "name": "Monterey Bay Whale Watch Grounds",
    "species": "Humpback",
    "info": "Feeding aggregations with birds; occasional orca encounters reported on some trips.",
    "date": "2025-10-04",
    "latitude": 36.618,
    "longitude": -121.901,
    "area": "USA (California, Monterey Bay)",
    "source": "https://gowhales.com/sightings/slstcurr/",
    "behaviors": [
      "nearshore",
      "surface activity"
    ]
  },
  {
    "id": "US-CA-MRY-20251005-05",
    "name": "Monterey Bay Whale Watch Grounds",
    "species": "Humpback",
    "info": "Feeding aggregations with birds; occasional orca encounters reported on some trips.",
    "date": "2025-10-05",
    "latitude": 36.618,
    "longitude": -121.901,
    "area": "USA (California, Monterey Bay)",
    "source": "https://gowhales.com/sightings/slstcurr/",
    "behaviors": [
      "nearshore",
      "surface activity"
    ]
  },
  {
    "id": "US-CA-MRY-20251006-06",
    "name": "Monterey Bay Whale Watch Grounds",
    "species": "Humpback",
    "info": "Feeding aggregations with birds; occasional orca encounters reported on some trips.",
    "date": "2025-10-06",
    "latitude": 36.618,
    "longitude": -121.901,
    "area": "USA (California, Monterey Bay)",
    "source": "https://gowhales.com/sightings/slstcurr/",
    "behaviors": [
      "nearshore",
      "surface activity"
    ]
  },
  {
    "id": "US-CA-MRY-20251007-07",
    "name": "Monterey Bay Whale Watch Grounds",
    "species": "Humpback",
    "info": "Feeding aggregations with birds; occasional orca encounters reported on some trips.",
    "date": "2025-10-07",
    "latitude": 36.618,
    "longitude": -121.901,
    "area": "USA (California, Monterey Bay)",
    "source": "https://gowhales.com/sightings/slstcurr/",
    "behaviors": [
      "nearshore",
      "surface activity"
    ]
  },
  {
    "id": "US-WA-SJS-20251001-01",
    "name": "Salish Sea \u2014 Rosario Strait/Anacortes",
    "species": "Humpback",
    "info": "Numerous humpbacks transiting and feeding; Bigg\u2019s orcas encountered intermittently.",
    "date": "2025-10-01",
    "latitude": 48.49,
    "longitude": -122.61,
    "area": "USA (Washington State, Salish Sea)",
    "source": "https://blog.island-adventures.com/",
    "behaviors": [
      "nearshore",
      "surface activity"
    ]
  },
  {
    "id": "US-WA-SJS-20251002-02",
    "name": "Salish Sea \u2014 Rosario Strait/Anacortes",
    "species": "Humpback",
    "info": "Numerous humpbacks transiting and feeding; Bigg\u2019s orcas encountered intermittently.",
    "date": "2025-10-02",
    "latitude": 48.49,
    "longitude": -122.61,
    "area": "USA (Washington State, Salish Sea)",
    "source": "https://blog.island-adventures.com/",
    "behaviors": [
      "nearshore",
      "surface activity"
    ]
  },
  {
    "id": "US-WA-SJS-20251003-03",
    "name": "Salish Sea \u2014 Rosario Strait/Anacortes",
    "species": "Humpback",
    "info": "Numerous humpbacks transiting and feeding; Bigg\u2019s orcas encountered intermittently.",
    "date": "2025-10-03",
    "latitude": 48.49,
    "longitude": -122.61,
    "area": "USA (Washington State, Salish Sea)",
    "source": "https://blog.island-adventures.com/",
    "behaviors": [
      "nearshore",
      "surface activity"
    ]
  },
  {
    "id": "US-WA-SJS-20251004-04",
    "name": "Salish Sea \u2014 Rosario Strait/Anacortes",
    "species": "Humpback",
    "info": "Numerous humpbacks transiting and feeding; Bigg\u2019s orcas encountered intermittently.",
    "date": "2025-10-04",
    "latitude": 48.49,
    "longitude": -122.61,
    "area": "USA (Washington State, Salish Sea)",
    "source": "https://blog.island-adventures.com/",
    "behaviors": [
      "nearshore",
      "surface activity"
    ]
  },
  {
    "id": "US-WA-SJS-20251005-05",
    "name": "Salish Sea \u2014 Rosario Strait/Anacortes",
    "species": "Humpback",
    "info": "Numerous humpbacks transiting and feeding; Bigg\u2019s orcas encountered intermittently.",
    "date": "2025-10-05",
    "latitude": 48.49,
    "longitude": -122.61,
    "area": "USA (Washington State, Salish Sea)",
    "source": "https://blog.island-adventures.com/",
    "behaviors": [
      "nearshore",
      "surface activity"
    ]
  },
  {
    "id": "US-WA-SJS-20251006-06",
    "name": "Salish Sea \u2014 Rosario Strait/Anacortes",
    "species": "Humpback",
    "info": "Numerous humpbacks transiting and feeding; Bigg\u2019s orcas encountered intermittently.",
    "date": "2025-10-06",
    "latitude": 48.49,
    "longitude": -122.61,
    "area": "USA (Washington State, Salish Sea)",
    "source": "https://blog.island-adventures.com/",
    "behaviors": [
      "nearshore",
      "surface activity"
    ]
  },
  {
    "id": "US-MA-STL-20251001-01",
    "name": "Stellwagen Bank \u2014 Cape Cod Bay",
    "species": "Humpback",
    "info": "Feeding groups with bubble-netting observed on multiple trips.",
    "date": "2025-10-01",
    "latitude": 42.33,
    "longitude": -70.25,
    "area": "USA (Massachusetts)",
    "source": "https://www.whalewatch.com/",
    "behaviors": [
      "nearshore",
      "surface activity"
    ]
  },
  {
    "id": "US-MA-STL-20251002-02",
    "name": "Stellwagen Bank \u2014 Cape Cod Bay",
    "species": "Humpback",
    "info": "Feeding groups with bubble-netting observed on multiple trips.",
    "date": "2025-10-02",
    "latitude": 42.33,
    "longitude": -70.25,
    "area": "USA (Massachusetts)",
    "source": "https://www.whalewatch.com/",
    "behaviors": [
      "nearshore",
      "surface activity"
    ]
  },
  {
    "id": "US-MA-STL-20251003-03",
    "name": "Stellwagen Bank \u2014 Cape Cod Bay",
    "species": "Humpback",
    "info": "Feeding groups with bubble-netting observed on multiple trips.",
    "date": "2025-10-03",
    "latitude": 42.33,
    "longitude": -70.25,
    "area": "USA (Massachusetts)",
    "source": "https://www.whalewatch.com/",
    "behaviors": [
      "nearshore",
      "surface activity"
    ]
  },
  {
    "id": "US-MA-STL-20251004-04",
    "name": "Stellwagen Bank \u2014 Cape Cod Bay",
    "species": "Humpback",
    "info": "Feeding groups with bubble-netting observed on multiple trips.",
    "date": "2025-10-04",
    "latitude": 42.33,
    "longitude": -70.25,
    "area": "USA (Massachusetts)",
    "source": "https://www.whalewatch.com/",
    "behaviors": [
      "nearshore",
      "surface activity"
    ]
  },
  {
    "id": "US-MA-STL-20251005-05",
    "name": "Stellwagen Bank \u2014 Cape Cod Bay",
    "species": "Humpback",
    "info": "Feeding groups with bubble-netting observed on multiple trips.",
    "date": "2025-10-05",
    "latitude": 42.33,
    "longitude": -70.25,
    "area": "USA (Massachusetts)",
    "source": "https://www.whalewatch.com/",
    "behaviors": [
      "nearshore",
      "surface activity"
    ]
  },
  {
    "id": "US-AK-IP-20251001-01",
    "name": "Inside Passage \u2014 Juneau/Stephens Passage",
    "species": "Humpback",
    "info": "Late-season humpbacks lingering near feeding grounds; occasional lunge feeding.",
    "date": "2025-10-01",
    "latitude": 58.3,
    "longitude": -134.4,
    "area": "USA (Alaska, Juneau region)",
    "source": "https://alaskawhalewatching.com/",
    "behaviors": [
      "nearshore",
      "surface activity"
    ]
  },
  {
    "id": "US-AK-IP-20251002-02",
    "name": "Inside Passage \u2014 Juneau/Stephens Passage",
    "species": "Humpback",
    "info": "Late-season humpbacks lingering near feeding grounds; occasional lunge feeding.",
    "date": "2025-10-02",
    "latitude": 58.3,
    "longitude": -134.4,
    "area": "USA (Alaska, Juneau region)",
    "source": "https://alaskawhalewatching.com/",
    "behaviors": [
      "nearshore",
      "surface activity"
    ]
  },
  {
    "id": "US-AK-IP-20251003-03",
    "name": "Inside Passage \u2014 Juneau/Stephens Passage",
    "species": "Humpback",
    "info": "Late-season humpbacks lingering near feeding grounds; occasional lunge feeding.",
    "date": "2025-10-03",
    "latitude": 58.3,
    "longitude": -134.4,
    "area": "USA (Alaska, Juneau region)",
    "source": "https://alaskawhalewatching.com/",
    "behaviors": [
      "nearshore",
      "surface activity"
    ]
  },
  {
    "id": "NO-TRO-ORC-20251006-01",
    "name": "Kv\u00e6nangen Fjord \u2014 Early Orca Arrivals",
    "species": "Orca",
    "info": "Operators begin spotting early-season orcas following herring schools.",
    "date": "2025-10-06",
    "latitude": 69.86,
    "longitude": 21.915,
    "area": "Norway (Troms og Finnmark)",
    "source": "https://whalewatchingtromso.com/swimming-with-orcas-in-norway/",
    "behaviors": [
      "nearshore",
      "surface activity"
    ]
  },
  {
    "id": "NO-TRO-ORC-20251007-02",
    "name": "Kv\u00e6nangen Fjord \u2014 Early Orca Arrivals",
    "species": "Orca",
    "info": "Operators begin spotting early-season orcas following herring schools.",
    "date": "2025-10-07",
    "latitude": 69.86,
    "longitude": 21.915,
    "area": "Norway (Troms og Finnmark)",
    "source": "https://whalewatchingtromso.com/swimming-with-orcas-in-norway/",
    "behaviors": [
      "nearshore",
      "surface activity"
    ]
  },
  {
    "id": "US-CA-MRB-20251004-01",
    "name": "Morro Bay Outside the Rock",
    "species": "Humpback",
    "info": "Calm conditions with active tail fluking and lunge feeding outside the harbor.",
    "date": "2025-10-04",
    "latitude": 35.37,
    "longitude": -120.86,
    "area": "USA (California, Morro Bay)",
    "source": "https://www.instagram.com/reel/DPenNNHEhAg/",
    "behaviors": [
      "nearshore",
      "surface activity"
    ]
  },
  {
    "id": "US-CA-MRB-20251005-02",
    "name": "Morro Bay Outside the Rock",
    "species": "Humpback",
    "info": "Calm conditions with active tail fluking and lunge feeding outside the harbor.",
    "date": "2025-10-05",
    "latitude": 35.37,
    "longitude": -120.86,
    "area": "USA (California, Morro Bay)",
    "source": "https://www.instagram.com/reel/DPenNNHEhAg/",
    "behaviors": [
      "nearshore",
      "surface activity"
    ]
  },
  {
    "id": "US-CA-MRB-20251006-03",
    "name": "Morro Bay Outside the Rock",
    "species": "Humpback",
    "info": "Calm conditions with active tail fluking and lunge feeding outside the harbor.",
    "date": "2025-10-06",
    "latitude": 35.37,
    "longitude": -120.86,
    "area": "USA (California, Morro Bay)",
    "source": "https://www.instagram.com/reel/DPenNNHEhAg/",
    "behaviors": [
      "nearshore",
      "surface activity"
    ]
  },
  {
    "id": "AU-NSW-SYD-2025-10-07-WS-1",
    "name": "Sydney Offshore \u2014 Northern run",
    "species": "Humpback",
    "info": "Breaching humpbacks reported on mid-day cruise; consistent pods throughout the day.",
    "date": "2025-10-07",
    "latitude": -33.9,
    "longitude": 151.3,
    "area": "Australia (New South Wales, Sydney)",
    "source": "https://www.whalewatchingsydney.com.au/whale-sightings/",
    "behaviors": [
      "breaching",
      "travelling"
    ]
  },
  {
    "id": "AU-NSW-SYD-2025-10-03-WS-2",
    "name": "Sydney Offshore \u2014 Shelf line",
    "species": "Humpback",
    "info": "Ecstatic breaching into swell on the 12pm cruise; more activity expected later.",
    "date": "2025-10-03",
    "latitude": -33.95,
    "longitude": 151.35,
    "area": "Australia (New South Wales, Sydney)",
    "source": "https://www.whalewatchingsydney.com.au/whale-sightings/",
    "behaviors": [
      "breaching",
      "surface activity"
    ]
  },
  {
    "id": "AU-WA-FRE-2025-10-03-WWWA-1",
    "name": "Fremantle \u2014 Humpback Grounds",
    "species": "Humpback",
    "info": "\u2018Humpback Whale Defence\u2019 encounter described on the Daily Whale blog.",
    "date": "2025-10-03",
    "latitude": -32.055,
    "longitude": 115.736,
    "area": "Australia (Western Australia, Fremantle/Perth)",
    "source": "https://whalewatchwesternaustralia.com/category/blog/",
    "behaviors": [
      "tail slap",
      "breaching",
      "with calf"
    ]
  },
  {
    "id": "AU-WA-FRE-2025-10-02-WWWA-2",
    "name": "Fremantle \u2014 Southbound Pods",
    "species": "Humpback",
    "info": "Multiple pods moving south; consistent sightings on early October departures.",
    "date": "2025-10-02",
    "latitude": -32.07,
    "longitude": 115.72,
    "area": "Australia (Western Australia, Fremantle/Perth)",
    "source": "https://whalewatchwesternaustralia.com/the-daily-whale/",
    "behaviors": [
      "travelling",
      "surface activity"
    ]
  },
  {
    "id": "AU-WA-FRE-2025-10-01-WWWA-3",
    "name": "Rottnest Channel \u2014 Mother & Calf",
    "species": "Humpback",
    "info": "Mother\u2013calf pairs transiting Rottnest Channel reported by local operators.",
    "date": "2025-10-01",
    "latitude": -31.997,
    "longitude": 115.438,
    "area": "Australia (Western Australia, Rottnest Channel)",
    "source": "https://whalewatchwesternaustralia.com/the-daily-whale/",
    "behaviors": [
      "with calf",
      "travelling"
    ]
  },
  {
    "id": "NZ-WGN-HBR-2025-10-06-WEL-ORC-1",
    "name": "Wellington Harbour \u2014 Evans Bay",
    "species": "Orca",
    "info": "Orcas filmed from Roseneath looking into Evans Bay; multiple animals close to shore.",
    "date": "2025-10-06",
    "latitude": -41.3,
    "longitude": 174.806,
    "area": "New Zealand (Wellington Harbour)",
    "source": "https://www.facebook.com/wellingtonnz/videos/orcas-around-wellington-harbour/403166417421655/",
    "behaviors": [
      "foraging",
      "nearshore"
    ]
  },
  {
    "id": "NZ-AKL-WHV-2025-10-05-ORC-2",
    "name": "Auckland \u2014 Westhaven Marina",
    "species": "Orca",
    "info": "Orcas filmed inside Westhaven Marina; very close to pontoons and seawall.",
    "date": "2025-10-05",
    "latitude": -36.842,
    "longitude": 174.75,
    "area": "New Zealand (Auckland, Waitemat\u0101 Harbour)",
    "source": "https://www.facebook.com/OrcasAreAmazing/videos/when-you-dont-even-need-to-step-on-a-boat-to-see-orcas-this-close-westhaven-mari/2876546569171580/",
    "behaviors": [
      "nearshore",
      "foraging"
    ]
  },
  {
    "id": "NZ-WGN-HBR-2025-10-04-HB-3",
    "name": "Wellington Harbour \u2014 Chaffers Passage",
    "species": "Humpback",
    "info": "Lone humpback exiting through Chaffers Passage toward Cook Strait.",
    "date": "2025-10-04",
    "latitude": -41.291,
    "longitude": 174.786,
    "area": "New Zealand (Wellington Harbour)",
    "source": "https://www.facebook.com/groups/554312507954499/posts/23903607935931627/",
    "behaviors": [
      "travelling",
      "blows"
    ]
  },
  {
    "id": "NZ-AKL-HG-2025-10-03-ORC-4",
    "name": "Hauraki Gulf \u2014 Rangitoto Channel",
    "species": "Orca",
    "info": "Orca observed near Rangitoto Lighthouse; approached small vessels calmly.",
    "date": "2025-10-03",
    "latitude": -36.788,
    "longitude": 174.856,
    "area": "New Zealand (Auckland, Hauraki Gulf)",
    "source": "https://www.nzherald.co.nz/nz/three-aucklanders-encounter-curious-juvenile-orca-on-morning-fishing-trip/XSLOQNU73JATZM7SUI5J627CDU/",
    "behaviors": [
      "curious approach",
      "nearshore"
    ]
  },
  {
    "id": "NZ-WGN-PLM-2025-10-02-ORC-5",
    "name": "Porirua/Plimmerton \u2014 Coast Run",
    "species": "Orca",
    "info": "Pod transiting south past Plimmerton on consecutive days per local watch group.",
    "date": "2025-10-02",
    "latitude": -41.071,
    "longitude": 174.868,
    "area": "New Zealand (Wellington region, Porirua/Plimmerton)",
    "source": "https://www.facebook.com/groups/1449950725311866/posts/2744217239218535/",
    "behaviors": [
      "travelling",
      "foraging"
    ]
  },
  {
    "id": "CA-BC-VIC-20251008-EW1",
    "name": "Victoria \u2014 Juan de Fuca / Haro Strait",
    "species": "Humpback",
    "info": "Humpbacks encountered with additional pinnipeds and seabirds on Oct 8 daily tour.",
    "date": "2025-10-08",
    "latitude": 48.37,
    "longitude": -123.11,
    "area": "Canada (BC/Victoria)",
    "source": "https://eaglewingtours.com/",
    "behaviors": [
      "foraging",
      "surface activity"
    ]
  },
  {
    "id": "US-WA-ANA-20251005-IA1",
    "name": "Rosario Strait / Anacortes",
    "species": "Humpback",
    "info": "Island Adventures report highlights multiple humpbacks on Oct 5.",
    "date": "2025-10-05",
    "latitude": 48.49,
    "longitude": -122.61,
    "area": "USA (Washington/Anacortes)",
    "source": "https://blog.island-adventures.com/",
    "behaviors": [
      "surface activity",
      "grouping"
    ]
  },
  {
    "id": "AU-WA-FRE-20251005-WWWA",
    "name": "Fremantle / Rottnest Channel",
    "species": "Humpback",
    "info": "Boisterous calves and competitive males observed on tours, Oct 5.",
    "date": "2025-10-05",
    "latitude": -32.055,
    "longitude": 115.743,
    "area": "Australia (WA/Fremantle)",
    "source": "https://whalewatchwesternaustralia.com/the-daily-whale/",
    "behaviors": [
      "calf with mother",
      "competitive males",
      "surface activity"
    ]
  },
  {
    "id": "ZA-CT-KALK-20251007-ORCA",
    "name": "Kalk Bay Harbour / False Bay",
    "species": "Orca",
    "info": "Two well-known orcas seen cruising near the harbour on Oct 7.",
    "date": "2025-10-07",
    "latitude": -34.127,
    "longitude": 18.449,
    "area": "South Africa (Cape Town/False Bay)",
    "source": "https://www.news24.com/southafrica/news/awesome-surprise-as-locals-welcome-rare-sighting-of-two-famous-orcas-in-cape-town-waters-20251007-1058",
    "behaviors": [
      "traveling",
      "nearshore"
    ]
  },
  {
    "id": "ZA-CT-GLEN-20251004-HB",
    "name": "Glencairn Beach / False Bay",
    "species": "Humpback",
    "info": "Humpback feeding observed off Glencairn Beach on Oct 4.",
    "date": "2025-10-04",
    "latitude": -34.137,
    "longitude": 18.433,
    "area": "South Africa (Cape Town/False Bay)",
    "source": "https://www.facebook.com/groups/1640190792677858/",
    "behaviors": [
      "foraging",
      "nearshore"
    ]
  },
  {
    "id": "NZ-WGN-ISLBAY-20250929-ORCA",
    "name": "Island Bay / Wellington",
    "species": "Orca",
    "info": "Multiple orca filmed close to shore around Island Bay on Sep 29.",
    "date": "2025-09-29",
    "latitude": -41.345,
    "longitude": 174.773,
    "area": "New Zealand (Wellington)",
    "source": "https://www.instagram.com/reel/DPNhLQNk6Vn/",
    "behaviors": [
      "nearshore",
      "traveling"
    ]
  }
]
